quantumsdk/__init__.py
quantumsdk/_utils.py
quantumsdk/client.py
quantumsdk/exceptions.py
quantumsdk/models/__init__.py
quantumsdk/models/base.py
quantumsdk/models/coupler.py
quantumsdk/models/crosstalk.py
quantumsdk/models/machine_state.py
quantumsdk/models/qubit.py
quantumsdk-0.2.3.dist-info/METADATA
quantumsdk-0.2.3.dist-info/WHEEL
quantumsdk-0.2.3.dist-info/RECORD
